drf_ext/__init__.py
drf_ext/metaclasses.py
drf_ext/metaclasses.py~
drf_ext/mixins.py
drf_ext/utils.py
drf_ext-0.1.1.dist-info/LICENSE
drf_ext-0.1.1.dist-info/METADATA
drf_ext-0.1.1.dist-info/WHEEL
drf_ext-0.1.1.dist-info/top_level.txt
drf_ext-0.1.1.dist-info/RECORD
