Metadata-Version: 2.1
Name: drf-ext
Version: 0.1.1
Summary: Extensions for the DRF
Home-page: https://github.com/heemayl/drf-ext
Author: Readul Hasan Chayan [Heemayl]
Author-email: me@heemayl.net
License: UNKNOWN
Project-URL: Bug Reports, https://github.com/heemayl/drf-ext/issues
Project-URL: Source, https://github.com/heemayl/drf-ext
Keywords: django django-rest django_rest rest development
Platform: UNKNOWN
Classifier: Development Status :: 5 - Production/Stable
Classifier: Intended Audience :: Developers
Classifier: License :: OSI Approved :: MIT License
Classifier: Programming Language :: Python :: 3
Classifier: Programming Language :: Python :: 3.6
Classifier: Programming Language :: Python :: 3.7
Classifier: Programming Language :: Python :: 3.8
Classifier: Programming Language :: Python :: 3.9
Requires-Python: >=3.6
Requires-Dist: djangorestframework
Provides-Extra: dev
Requires-Dist: pytest-django ; extra == 'dev'
Requires-Dist: factory-boy ; extra == 'dev'
